cli/.flake8
cli/__init__.py
cli/__main__.py
cli/build.py
cli/commands/README.md
cli/commands/__init__.py
cli/commands/destroy.py
cli/commands/setup.py
cli/commands/workload/README.md
cli/commands/workload/__init__.py
cli/commands/workload/bootstrap.py
cli/commands/workload/create.py
cli/commands/workload/delete.py
cli/commands/workload/workload.py
cli/common/__init__.py
cli/common/const/__init__.py
cli/common/const/common_path.py
cli/common/const/const.py
cli/common/const/namespaces.py
cli/common/const/parameter_names.py
cli/common/custom_excpetions.py
cli/common/enums/__init__.py
cli/common/enums/cloud_providers.py
cli/common/enums/dns_registrars.py
cli/common/enums/git_plans.py
cli/common/enums/git_providers.py
cli/common/logging_config.py
cli/common/retry_decorator.py
cli/common/singleton_metaclass.py
cli/common/state_store.py
cli/common/tracing_decorator.py
cli/common/utils/__init__.py
cli/common/utils/command_utils.py
cli/common/utils/generators.py
cli/common/utils/os_utils.py
cli/services/README.md
cli/services/__init__.py
cli/services/cloud/__init__.py
cli/services/cloud/aws/__init__.py
cli/services/cloud/aws/aws_manager.py
cli/services/cloud/aws/aws_sdk.py
cli/services/cloud/aws/aws_session_manager.py
cli/services/cloud/aws/iam_permissions.py
cli/services/cloud/azure/__init__.py
cli/services/cloud/azure/azure_manager.py
cli/services/cloud/azure/azure_sdk.py
cli/services/cloud/azure/iam_permissions.py
cli/services/cloud/cloud_provider_manager.py
cli/services/dependency_manager.py
cli/services/dns/__init__.py
cli/services/dns/azure_dns/__init__.py
cli/services/dns/azure_dns/azure_dns.py
cli/services/dns/dns_provider_manager.py
cli/services/dns/route53/__init__.py
cli/services/dns/route53/route53.py
cli/services/k8s/__init__.py
cli/services/k8s/config_builder.py
cli/services/k8s/delivery_service_manager.py
cli/services/k8s/k8s.py
cli/services/k8s/kctl_wrapper.py
cli/services/k8s/kubeconfig.yaml
cli/services/keys/__init__.py
cli/services/keys/key_manager.py
cg_devx_core-0.4.0.dist-info/METADATA
cg_devx_core-0.4.0.dist-info/WHEEL
cg_devx_core-0.4.0.dist-info/entry_points.txt
cg_devx_core-0.4.0.dist-info/RECORD
