Metadata-Version: 2.1
Name: cg-devx-core
Version: 0.4.0
Summary: 
Author: Alexander Ulyanov
Author-email: alexu@cloudgeometry.io
Requires-Python: >=3.10,<3.11
Classifier: Programming Language :: Python :: 3
Classifier: Programming Language :: Python :: 3.10
Requires-Dist: PyInstaller (==5.13.2)
Requires-Dist: alive-progress (>=3.1.5,<4.0.0)
Requires-Dist: awscli (==1.29.56)
Requires-Dist: azure-identity (==1.14.0)
Requires-Dist: azure-mgmt-authorization (>=4.0.0,<5.0.0)
Requires-Dist: azure-mgmt-compute (>=30.5.0,<31.0.0)
Requires-Dist: azure-mgmt-containerservice (>=26.0.0,<27.0.0)
Requires-Dist: azure-mgmt-dns (>=8.1.0,<9.0.0)
Requires-Dist: azure-mgmt-privatedns (>=1.1.0,<2.0.0)
Requires-Dist: azure-mgmt-resource (==23.0.1)
Requires-Dist: azure-mgmt-storage (>=21.1.0,<22.0.0)
Requires-Dist: azure-mgmt-subscription (>=3.1.1,<4.0.0)
Requires-Dist: azure-storage-blob (==12.17.0)
Requires-Dist: boto3 (==1.28.56)
Requires-Dist: click (==8.1.7)
Requires-Dist: cloup (==3.0.2)
Requires-Dist: configparser (==6.0.0)
Requires-Dist: dnspython (==2.4.2)
Requires-Dist: gcloud (==0.18.3)
Requires-Dist: ghrepo (==0.7.0)
Requires-Dist: gitpython (==3.1.32)
Requires-Dist: httpx (==0.25.0)
Requires-Dist: hvac (==1.2.1)
Requires-Dist: kubernetes (==27.2.0)
Requires-Dist: portforward (>=0.6.0,<0.7.0)
Requires-Dist: pyyaml (==6.0.1)
